timshive/__init__.py
timshive/timshive.py
timshive-0.1.4.dist-info/METADATA
timshive-0.1.4.dist-info/WHEEL
timshive-0.1.4.dist-info/top_level.txt
timshive-0.1.4.dist-info/RECORD
