Metadata-Version: 2.1
Name: timshive
Version: 0.1.4
Summary: Program for creating simple hive plots in python using multidimensional arrays.
Home-page: UNKNOWN
Author: Tim Crimmins
Author-email: tim.g.crimmins@gmail.com
License: MIT
Platform: UNKNOWN
Classifier: Development Status :: 4 - Beta
Classifier: Topic :: Scientific/Engineering :: Visualization
Classifier: Programming Language :: Python :: 3
Requires-Dist: matplotlib
Requires-Dist: numpy
